mateo_pip/__init__.py
mateo_pip/aurora_database.py
mateo_pip/example.py
mateo_pip-0.0.7.dist-info/METADATA
mateo_pip-0.0.7.dist-info/WHEEL
mateo_pip-0.0.7.dist-info/licenses/LICENSE
mateo_pip-0.0.7.dist-info/RECORD
