Metadata-Version: 2.1
Name: mateo_pip
Version: 0.0.7
Summary: Testing package
Project-URL: Homepage, https://github.com/pypa/sampleproject
Project-URL: Issues, https://github.com/pypa/sampleproject/issues
Author-email: Matt <mateousme@melonn.com>
License-File: LICENSE
Classifier: License :: OSI Approved :: MIT License
Classifier: Operating System :: OS Independent
Classifier: Programming Language :: Python :: 3
Requires-Python: >=3.10
Requires-Dist: mysql-connector-python==8.1.0
Requires-Dist: pandas==2.1.1
